{ "type": "Feature", "properties": { "N_de_lot": 406.0, "_N_dossier": "1770\/18", "_D_dep_demande": "25\/06\/2018", "_R_socia_arabe": "ش ذ م م هالث أسباير ميديك ", "_N_P_gerant_arabe": "هسة عمر", "_R_socia_français": "SARL HEALTH ASPIRE MEDIC", "_N_P_gerant_français": "HASSA AMAR ", "_Adresse": "BT A 12 N° 114 ,500 LOGTS CITE NOUREDDINE MAIZA SETIF ", "_N_tele": "036 82 65 25\n0661 66 12 20  ", "_Fax": "036 82 65 29", "_Email": null, "_Int_projet_arabe": "وحدة لانتاج الريزين الطبي للصناعات الارتوبيديك", "_Int_projet_français": "UNITE DE RESINE MEDICALE POUR FABRICATION ORTHOPEDIQUE ", "_Sect_Activite": "INDUSTRIE", "_Fil_Indust": "PHARMACIE", "_Su_demand_m²": "15000", "_Mont_Investis_Millions_DA": 538260112.0, "_Nomb_emploi": 110.0, "_D_examen_demande_PV": "16\/07\/2018", "_N_decision": "\/", "_Su_octroyee_m²": 15000.0, "_Locali_projet": "OULED SABER", "_Commune": "OULED SABER", "_Site": "ZI", "_P_droi_Etude_vrd": null, "_N_Arr_conces": null, "_D_Arret_conces": null, "_Mont_conces": null, "_Dat_paiem": null, "_N_Act_conces": null, "_Da_Acte_conces": null, "_N_Act_cession": null, "_Dat_Acte_cession": null, "_N_depot_permis_de_const": null, "_D_depot_dospermis_de_construire": null, "_Avis_services": null, "_N_Arrt_perm_const": null, "_Da_Arrt_permi_constr": null, "_Dat_Depot_Dossier": null, "_Dat_Approb_EIE": null, "_Dat_Deci_Cre_Prealabre": null, "_N_Arrt_Exploit": null, "_Dat_Arrt_Exploit": null, "_N_Depot_doss": null, "_Date_Depot_dossier": null, "_N_Deci_ANDI": null, "_Taux_avance_travaux": null, "_Taux_avance_investis": null, "_Mise_en_service_oui_non": null, "_Emplois_reel": null, "_Changem_statut": null, "_Observation": null }, "geometry": { "type": "Polygon", "coordinates": [ [ [ 5.552416338662848, 36.164978029726043 ], [ 5.552542602707444, 36.164934134534796 ], [ 5.551638182221801, 36.163518584904971 ], [ 5.551172334617086, 36.163714286489643 ], [ 5.550786650539927, 36.163876308519349 ], [ 5.551658806307683, 36.165241380789716 ], [ 5.552416338662848, 36.164978029726043 ] ] ] } }
