{ "type": "Feature", "properties": { "N_de_lot": 314.0, "_N_dossier": "170\/16", "_D_dep_demande": "15\/05\/2016", "_R_socia_arabe": "كزعي بهاء الدين أكرم ", "_N_P_gerant_arabe": "كزعي بهاء الدين أكرم ", "_R_socia_français": "KEZAI BAHAA EDDINE AKRAM", "_N_P_gerant_français": "KEZAI BAHAA EDDINE AKRAM", "_Adresse": "PROMOTION FERKOUSSE BOUAROUA SETIF", "_N_tele": "05 50 76 93 43", "_Fax": null, "_Email": null, "_Int_projet_arabe": "وحدة لصناعة البوليستيران ", "_Int_projet_français": "UNITE DE FABRICATION DE POLYSTYRENE", "_Sect_Activite": "INDUSTRIE", "_Fil_Indust": "PAPIER-PLASTIQUE", "_Su_demand_m²": "5000", "_Mont_Investis_Millions_DA": 176000000.0, "_Nomb_emploi": 25.0, "_D_examen_demande_PV": "06\/06\/2016\n14\/12\/2017", "_N_decision": "1985\/16", "_Su_octroyee_m²": 5000.0, "_Locali_projet": "OULED SABER", "_Commune": "OULED SABER", "_Site": "ZI", "_P_droi_Etude_vrd": null, "_N_Arr_conces": null, "_D_Arret_conces": null, "_Mont_conces": null, "_Dat_paiem": null, "_N_Act_conces": null, "_Da_Acte_conces": null, "_N_Act_cession": null, "_Dat_Acte_cession": null, "_N_depot_permis_de_const": null, "_D_depot_dospermis_de_construire": null, "_Avis_services": null, "_N_Arrt_perm_const": null, "_Da_Arrt_permi_constr": null, "_Dat_Depot_Dossier": null, "_Dat_Approb_EIE": null, "_Dat_Deci_Cre_Prealabre": null, "_N_Arrt_Exploit": null, "_Dat_Arrt_Exploit": null, "_N_Depot_doss": null, "_Date_Depot_dossier": null, "_N_Deci_ANDI": null, "_Taux_avance_travaux": null, "_Taux_avance_investis": null, "_Mise_en_service_oui_non": null, "_Emplois_reel": null, "_Changem_statut": null, "_Observation": null }, "geometry": { "type": "Polygon", "coordinates": [ [ [ 5.562466334323355, 36.174171114344226 ], [ 5.56241263555174, 36.173271188097218 ], [ 5.561857660245228, 36.173292955857001 ], [ 5.561911352707995, 36.174192882604792 ], [ 5.562466334323355, 36.174171114344226 ] ] ] } }
