{ "type": "Feature", "properties": { "N_de_lot": 331.0, "_N_dossier": "177\/16", "_D_dep_demande": "18\/05\/2016", "_R_socia_arabe": "ش ذ م م لطفي الكترونيكس", "_N_P_gerant_arabe": " مباركية مبروك ", "_R_socia_français": "SARL LOUTFU ELECTRONIX", "_N_P_gerant_français": "MEBARKIA MEBROUK", "_Adresse": "ZONE D ACTIVITE BBA", "_N_tele": "0550960666\n035873134\n035873158", "_Fax": null, "_Email": null, "_Int_projet_arabe": "وحدة لتركيب الأجهزة الالكترونية ", "_Int_projet_français": "UNITE DE MONTAGE ELECTRONIQUE (GEANT)", "_Sect_Activite": "INDUSTRIE", "_Fil_Indust": "ELECTRIQUES ET  ELECTOMENAGERS", "_Su_demand_m²": "30000", "_Mont_Investis_Millions_DA": 693120000.0, "_Nomb_emploi": 200.0, "_D_examen_demande_PV": "06\/06\/2016\n14\/12\/2017\n14\/12\/2017", "_N_decision": "2130\/16", "_Su_octroyee_m²": 27912.0, "_Locali_projet": "OULED SABER", "_Commune": "OULED SABER", "_Site": "ZI", "_P_droi_Etude_vrd": null, "_N_Arr_conces": null, "_D_Arret_conces": null, "_Mont_conces": null, "_Dat_paiem": null, "_N_Act_conces": null, "_Da_Acte_conces": null, "_N_Act_cession": null, "_Dat_Acte_cession": null, "_N_depot_permis_de_const": null, "_D_depot_dospermis_de_construire": null, "_Avis_services": null, "_N_Arrt_perm_const": null, "_Da_Arrt_permi_constr": null, "_Dat_Depot_Dossier": null, "_Dat_Approb_EIE": null, "_Dat_Deci_Cre_Prealabre": null, "_N_Arrt_Exploit": null, "_Dat_Arrt_Exploit": null, "_N_Depot_doss": null, "_Date_Depot_dossier": null, "_N_Deci_ANDI": null, "_Taux_avance_travaux": null, "_Taux_avance_investis": null, "_Mise_en_service_oui_non": null, "_Emplois_reel": null, "_Changem_statut": null, "_Observation": null }, "geometry": { "type": "Polygon", "coordinates": [ [ [ 5.545211385154429, 36.17255133514508 ], [ 5.545151252684727, 36.171539809365619 ], [ 5.5451481291653, 36.171520024750158 ], [ 5.545141198152077, 36.171500886237709 ], [ 5.545130632979786, 36.171482872334259 ], [ 5.545116697256104, 36.171466434388918 ], [ 5.545099740010035, 36.171451984079248 ], [ 5.54508018417534, 36.171439881038189 ], [ 5.545058520890514, 36.171430428468888 ], [ 5.545035290264812, 36.171423862738514 ], [ 5.545011074567607, 36.171420349016657 ], [ 5.544986477971143, 36.171419973594716 ], [ 5.542667001581428, 36.171533583863983 ], [ 5.542733224637693, 36.172648157124499 ], [ 5.545211385154429, 36.17255133514508 ] ] ] } }
