{ "type": "Feature", "properties": { "N_de_lot": 104.0, "_N_dossier": "204\/16", "_D_dep_demande": "25\/05\/2016", "_R_socia_arabe": " ش ذ م م أش تي كومباني", "_N_P_gerant_arabe": "ذبيح حمزة", "_R_socia_français": "SARL DHT COMPANY ", "_N_P_gerant_français": "DEBIH HAMZA", "_Adresse": "CITE 360 LOGTS BTS C1 N 49 SETIF", "_N_tele": "0661709112\n0550926507\n036747556\/57", "_Fax": null, "_Email": null, "_Int_projet_arabe": "وحدة لصناعة مبردات المركبات ", "_Int_projet_français": "UNITE DE FABRICATION DE RADIATEURS POUR VEHICULES", "_Sect_Activite": "INDUSTRIE", "_Fil_Indust": "MECANIQUE ET  AUTOMOBILE", "_Su_demand_m²": "25000", "_Mont_Investis_Millions_DA": 1220000000.0, "_Nomb_emploi": 150.0, "_D_examen_demande_PV": "06\/06\/2016\n15\/06\/2017", "_N_decision": "1955\/16", "_Su_octroyee_m²": 25000.0, "_Locali_projet": "OULED SABER", "_Commune": "OULED SABER", "_Site": "ZI", "_P_droi_Etude_vrd": null, "_N_Arr_conces": null, "_D_Arret_conces": null, "_Mont_conces": null, "_Dat_paiem": null, "_N_Act_conces": null, "_Da_Acte_conces": null, "_N_Act_cession": null, "_Dat_Acte_cession": null, "_N_depot_permis_de_const": null, "_D_depot_dospermis_de_construire": null, "_Avis_services": null, "_N_Arrt_perm_const": null, "_Da_Arrt_permi_constr": null, "_Dat_Depot_Dossier": null, "_Dat_Approb_EIE": null, "_Dat_Deci_Cre_Prealabre": null, "_N_Arrt_Exploit": null, "_Dat_Arrt_Exploit": null, "_N_Depot_doss": null, "_Date_Depot_dossier": null, "_N_Deci_ANDI": null, "_Taux_avance_travaux": null, "_Taux_avance_investis": null, "_Mise_en_service_oui_non": null, "_Emplois_reel": null, "_Changem_statut": null, "_Observation": null }, "geometry": { "type": "Polygon", "coordinates": [ [ [ 5.547732600605912, 36.181657700243953 ], [ 5.547623577827279, 36.179857899799039 ], [ 5.54668015203366, 36.179894784616536 ], [ 5.54654437244882, 36.180135044378716 ], [ 5.546485827529376, 36.180231003103849 ], [ 5.546420357399001, 36.180323973592195 ], [ 5.546348192679256, 36.180413628260645 ], [ 5.546269587705178, 36.180499650737659 ], [ 5.546184819443731, 36.180581736787609 ], [ 5.546155552080867, 36.180608426015503 ], [ 5.546221470794799, 36.181716777953881 ], [ 5.547732600605912, 36.181657700243953 ] ] ] } }
