{ "type": "Feature", "properties": { "N_de_lot": 357.0, "_N_dossier": null, "_D_dep_demande": null, "_R_socia_arabe": null, "_N_P_gerant_arabe": null, "_R_socia_français": null, "_N_P_gerant_français": null, "_Adresse": null, "_N_tele": null, "_Fax": null, "_Email": null, "_Int_projet_arabe": null, "_Int_projet_français": null, "_Sect_Activite": null, "_Fil_Indust": null, "_Su_demand_m²": null, "_Mont_Investis_Millions_DA": null, "_Nomb_emploi": null, "_D_examen_demande_PV": null, "_N_decision": null, "_Su_octroyee_m²": null, "_Locali_projet": null, "_Commune": null, "_Site": null, "_P_droi_Etude_vrd": null, "_N_Arr_conces": null, "_D_Arret_conces": null, "_Mont_conces": null, "_Dat_paiem": null, "_N_Act_conces": null, "_Da_Acte_conces": null, "_N_Act_cession": null, "_Dat_Acte_cession": null, "_N_depot_permis_de_const": null, "_D_depot_dospermis_de_construire": null, "_Avis_services": null, "_N_Arrt_perm_const": null, "_Da_Arrt_permi_constr": null, "_Dat_Depot_Dossier": null, "_Dat_Approb_EIE": null, "_Dat_Deci_Cre_Prealabre": null, "_N_Arrt_Exploit": null, "_Dat_Arrt_Exploit": null, "_N_Depot_doss": null, "_Date_Depot_dossier": null, "_N_Deci_ANDI": null, "_Taux_avance_travaux": null, "_Taux_avance_investis": null, "_Mise_en_service_oui_non": null, "_Emplois_reel": null, "_Changem_statut": null, "_Observation": null }, "geometry": { "type": "Polygon", "coordinates": [ [ [ 5.570467951172134, 36.172774543270585 ], [ 5.570359871535299, 36.170966256918419 ], [ 5.570297042278131, 36.170943279859593 ], [ 5.570238965767964, 36.170924642235889 ], [ 5.570178991746848, 36.17091049411686 ], [ 5.570117648867719, 36.170900957535459 ], [ 5.570055474573252, 36.170896117383883 ], [ 5.569993013808987, 36.170896016033616 ], [ 5.569715758113004, 36.170906106940095 ], [ 5.569030675138967, 36.170931038097152 ], [ 5.569143936838437, 36.172826559102127 ], [ 5.570467951172134, 36.172774543270585 ] ] ] } }
