{ "type": "Feature", "properties": { "N_de_lot": 62.0, "_N_dossier": "280\/16", "_D_dep_demande": "14\/06\/2016", "_R_socia_arabe": "م ش و ذ م م ميرا بلاست", "_N_P_gerant_arabe": "عمراني واجي", "_R_socia_français": "EURL MIRA PLASTE", "_N_P_gerant_français": "AMRANI OUAJI", "_Adresse": "RUE MEZLOUG MOHAMED N 69 CITE GASRIA SETIF", "_N_tele": "0555050514\n0555618360\n036930575\n036938581", "_Fax": null, "_Email": null, "_Int_projet_arabe": "وحدة لانتاج أدوات التنظيف و البستنة و صناعة القوالب ", "_Int_projet_français": "UNITE DE FABRICATION D’ARTICLES DE MENAGE ET  DE JARDINAGE ET  FABRICATION DE MOULES POUR INJECTION", "_Sect_Activite": "INDUSTRIE", "_Fil_Indust": "SIDERURGIE ET  METALLURGIE", "_Su_demand_m²": "10000", "_Mont_Investis_Millions_DA": 518450000.0, "_Nomb_emploi": 160.0, "_D_examen_demande_PV": "25\/07\/2016\n18\/05\/2017\n09\/07\/2018", "_N_decision": "1975\/16", "_Su_octroyee_m²": 10000.0, "_Locali_projet": "OULED SABER", "_Commune": "OULED SABER", "_Site": "ZI", "_P_droi_Etude_vrd": null, "_N_Arr_conces": null, "_D_Arret_conces": null, "_Mont_conces": null, "_Dat_paiem": null, "_N_Act_conces": null, "_Da_Acte_conces": null, "_N_Act_cession": null, "_Dat_Acte_cession": null, "_N_depot_permis_de_const": null, "_D_depot_dospermis_de_construire": null, "_Avis_services": null, "_N_Arrt_perm_const": null, "_Da_Arrt_permi_constr": null, "_Dat_Depot_Dossier": null, "_Dat_Approb_EIE": null, "_Dat_Deci_Cre_Prealabre": null, "_N_Arrt_Exploit": null, "_Dat_Arrt_Exploit": null, "_N_Depot_doss": null, "_Date_Depot_dossier": null, "_N_Deci_ANDI": null, "_Taux_avance_travaux": null, "_Taux_avance_investis": null, "_Mise_en_service_oui_non": null, "_Emplois_reel": null, "_Changem_statut": null, "_Observation": null }, "geometry": { "type": "Polygon", "coordinates": [ [ [ 5.565766847968258, 36.182935636206849 ], [ 5.56571741578116, 36.182036413153355 ], [ 5.565162285186068, 36.182056467536704 ], [ 5.565162468546551, 36.182059804690986 ], [ 5.565211806453054, 36.18295742220873 ], [ 5.565766847968258, 36.182935636206849 ] ] ] } }
